spatialise_soil_prediction/__init__.py
spatialise_soil_prediction/_base_client.py
spatialise_soil_prediction/_client.py
spatialise_soil_prediction/_compat.py
spatialise_soil_prediction/_constants.py
spatialise_soil_prediction/_exceptions.py
spatialise_soil_prediction/_files.py
spatialise_soil_prediction/_models.py
spatialise_soil_prediction/_qs.py
spatialise_soil_prediction/_resource.py
spatialise_soil_prediction/_response.py
spatialise_soil_prediction/_streaming.py
spatialise_soil_prediction/_types.py
spatialise_soil_prediction/_version.py
spatialise_soil_prediction/py.typed
spatialise_soil_prediction/_utils/__init__.py
spatialise_soil_prediction/_utils/_logs.py
spatialise_soil_prediction/_utils/_proxy.py
spatialise_soil_prediction/_utils/_reflection.py
spatialise_soil_prediction/_utils/_resources_proxy.py
spatialise_soil_prediction/_utils/_streams.py
spatialise_soil_prediction/_utils/_sync.py
spatialise_soil_prediction/_utils/_transform.py
spatialise_soil_prediction/_utils/_typing.py
spatialise_soil_prediction/_utils/_utils.py
spatialise_soil_prediction/lib/.keep
spatialise_soil_prediction/resources/__init__.py
spatialise_soil_prediction/resources/batch.py
spatialise_soil_prediction/resources/health.py
spatialise_soil_prediction/types/__init__.py
spatialise_soil_prediction/types/batch_create_params.py
spatialise_soil_prediction/types/batch_create_response.py
spatialise_soil_prediction/types/batch_retrieve_status_params.py
spatialise_soil_prediction/types/batch_retrieve_status_response.py
spatialise_soil_prediction/types/batch_status.py
spatialise_soil_prediction-0.1.0.dist-info/METADATA
spatialise_soil_prediction-0.1.0.dist-info/WHEEL
spatialise_soil_prediction-0.1.0.dist-info/licenses/LICENSE
spatialise_soil_prediction-0.1.0.dist-info/RECORD
